Metadata-Version: 1.0
Name: zettwerk.i18nduder
Version: 0.2
Summary: A helper/wrapper script for i18ndude to easier working with translation files in a common plone environment.
Home-page: http://zettwerk.com
Author: zettwerk GmbH
Author-email: jk@zettwerk.com
License: GPL
Keywords: plone,i18ndude
Platform: UNKNOWN
Classifier: Framework :: Plone
Classifier: Programming Language :: Python
